raep/__init__.py
raep/cli.py
raep/enzyme_xgb_model.pkl
raep/model.py
raep-1.0.0.dist-info/METADATA
raep-1.0.0.dist-info/WHEEL
raep-1.0.0.dist-info/entry_points.txt
raep-1.0.0.dist-info/top_level.txt
raep-1.0.0.dist-info/RECORD
