Metadata-Version: 2.4
Name: raep
Version: 1.0.0
Summary: Random Forest Enzyme Prediction
Author-email: DHY <dhy.scut@outlook.com>
License: MIT
Classifier: License :: OSI Approved :: MIT License
Classifier: Programming Language :: Python :: 3
Classifier: Intended Audience :: Science/Research
Requires-Python: >=3.7
Requires-Dist: numpy
Requires-Dist: pandas
Requires-Dist: scikit-learn
Requires-Dist: xgboost
Requires-Dist: joblib
